README.md
setup.py
app/__init__.py
app/backends.py
app/cli.py
app/config.py
app/exceptions.py
app/main.py
fast_query_store.egg-info/PKG-INFO
fast_query_store.egg-info/SOURCES.txt
fast_query_store.egg-info/dependency_links.txt
fast_query_store.egg-info/entry_points.txt
fast_query_store.egg-info/requires.txt
fast_query_store.egg-info/top_level.txt