Metadata-Version: 2.1
Name: fast-query-store
Version: 0.0.7.dev0
Summary: A Fast Backend API for database queries
Home-page: https://github.com/rhenanbartels/fast-query-store
Author: Rhenan and Turicas
Author-email: rhenan.bartels@gmail.com
License: UNKNOWN
Project-URL: Bug Tracker, https://github.com/rhenanbartels/fast-query-store/issues
Platform: UNKNOWN
Classifier: Programming Language :: Python :: 3
Classifier: License :: OSI Approved :: MIT License
Classifier: Operating System :: OS Independent
Requires-Python: >=3.8
